.DS_Store
hopeprattmypythonlib/__init__.py
hopeprattmypythonlib/myfunctions.py
hopeprattmypythonlib-0.1.0.dist-info/METADATA
hopeprattmypythonlib-0.1.0.dist-info/WHEEL
hopeprattmypythonlib-0.1.0.dist-info/top_level.txt
hopeprattmypythonlib-0.1.0.dist-info/RECORD
